[
    {
        "rank": "1",
        "title": "그대 작은 나의 세상이 되어",
        "artist": "카더가든",
        "imageURL": "https://image.bugsm.co.kr/album/images/50/40271/4027190.jpg?version=20230112170034",
        "album": "부재"
    },
    {
        "rank": "2",
        "title": "Good Goodbye",
        "artist": "화사 (HWASA)",
        "imageURL": "https://image.bugsm.co.kr/album/images/50/41305/4130508.jpg?version=20251028010926",
        "album": "Good Goodbye"
    },
    {
        "rank": "3",
        "title": "Backseat Promises",
        "artist": "강다니엘(KANG DANIEL)",
        "imageURL": "https://image.bugsm.co.kr/album/images/50/41355/4135587.jpg?version=20251219011404",
        "album": "PULSEPHASE"
    },
    {
        "rank": "4",
        "title": "사랑하게 될 거야",
        "artist": "한로로",
        "imageURL": "https://image.bugsm.co.kr/album/images/50/205869/20586963.jpg?version=20240904004214",
        "album": "이상비행"
    },
    {
        "rank": "5",
        "title": "0+0",
        "artist": "한로로",
        "imageURL": "https://image.bugsm.co.kr/album/images/50/207447/20744778.jpg?version=20250804122248",
        "album": "자몽살구클럽"
    },
    {
        "rank": "6",
        "title": "404 (New Era)",
        "artist": "KiiiKiii (키키)",
        "imageURL": "https://image.bugsm.co.kr/album/images/50/41388/4138853.jpg?version=20260127003833",
        "album": "Delulu Pack"
    },
    {
        "rank": "7",
        "title": "Blue Valentine",
        "artist": "NMIXX",
        "imageURL": "https://image.bugsm.co.kr/album/images/50/41299/4129960.jpg?version=20251108012458",
        "album": "Blue Valentine"
    },
    {
        "rank": "8",
        "title": "Drowning",
        "artist": "WOODZ",
        "imageURL": "https://image.bugsm.co.kr/album/images/50/40839/4083984.jpg?version=20250318143138",
        "album": "OO-LI"
    },
    {
        "rank": "9",
        "title": "like JENNIE",
        "artist": "제니 (JENNIE)",
        "imageURL": "https://image.bugsm.co.kr/album/images/50/41159/4115971.jpg?version=20250322025325",
        "album": "Ruby"
    },
    {
        "rank": "10",
        "title": "OVERDRIVE",
        "artist": "TWS (투어스)",
        "imageURL": "https://image.bugsm.co.kr/album/images/50/41288/4128834.jpg?version=20251014031813",
        "album": "TWS 4th Mini Album ‘play hard’"
    },
    {
        "rank": "11",
        "title": "NOT CUTE ANYMORE",
        "artist": "아일릿(ILLIT)",
        "imageURL": "https://image.bugsm.co.kr/album/images/50/41342/4134249.jpg?version=20251129010313",
        "album": "NOT CUTE ANYMORE"
    },
    {
        "rank": "12",
        "title": "SPAGHETTI (feat. j-hope of BTS)",
        "artist": "LE SSERAFIM (르세라핌)",
        "imageURL": "https://image.bugsm.co.kr/album/images/50/41314/4131460.jpg?version=20251028011200",
        "album": "SPAGHETTI"
    },
    {
        "rank": "13",
        "title": "타임캡슐",
        "artist": "다비치",
        "imageURL": "https://image.bugsm.co.kr/album/images/50/41306/4130608.jpg?version=20251017094801",
        "album": "타임캡슐"
    },
    {
        "rank": "14",
        "title": "Golden",
        "artist": "HUNTR/X",
        "imageURL": "https://image.bugsm.co.kr/album/images/50/381763/38176338.jpg?version=20250927005933",
        "album": "KPop Demon Hunters (Soundtrack from the Netflix Film)"
    },
    {
        "rank": "15",
        "title": "Obsession (情結)",
        "artist": "강다니엘(KANG DANIEL)",
        "imageURL": "https://image.bugsm.co.kr/album/images/50/207848/20784852.jpg?version=20260128012653",
        "album": "Obsession (情結)"
    },
    {
        "rank": "16",
        "title": "toxic till the end",
        "artist": "로제(ROSÉ)",
        "imageURL": "https://image.bugsm.co.kr/album/images/50/41113/4111311.jpg?version=20250319100710",
        "album": "rosie"
    },
    {
        "rank": "17",
        "title": "사랑은 봄비처럼... 이별은 겨울비처럼",
        "artist": "임현정",
        "imageURL": "https://image.bugsm.co.kr/album/images/50/306/30639.jpg?version=20230701040734",
        "album": "A Year Out..In The Island"
    },
    {
        "rank": "18",
        "title": "Mono (Feat. skaiwater)",
        "artist": "i-dle (아이들)",
        "imageURL": "https://image.bugsm.co.kr/album/images/50/41391/4139172.jpg?version=20260128020348",
        "album": "Mono (Feat. skaiwater)"
    },
    {
        "rank": "19",
        "title": "멸종위기사랑",
        "artist": "이찬혁",
        "imageURL": "https://image.bugsm.co.kr/album/images/50/41229/4122969.jpg?version=20250729020842",
        "album": "EROS"
    },
    {
        "rank": "20",
        "title": "뛰어(JUMP)",
        "artist": "BLACKPINK",
        "imageURL": "https://image.bugsm.co.kr/album/images/50/41229/4122947.jpg?version=20250712005750",
        "album": "뛰어(JUMP)"
    },
    {
        "rank": "21",
        "title": "하얀 그리움",
        "artist": "프로미스나인",
        "imageURL": "https://image.bugsm.co.kr/album/images/50/207742/20774246.jpg?version=20251203012355",
        "album": "하얀 그리움"
    },
    {
        "rank": "22",
        "title": "ONE MORE TIME",
        "artist": "ALLDAY PROJECT",
        "imageURL": "https://image.bugsm.co.kr/album/images/50/41335/4133502.jpg?version=20251209003718",
        "album": "ALLDAY PROJECT"
    },
    {
        "rank": "23",
        "title": "FOCUS",
        "artist": "Hearts2Hearts (하츠투하츠)",
        "imageURL": "https://image.bugsm.co.kr/album/images/50/41289/4128980.jpg?version=20251022002830",
        "album": "FOCUS - The 1st Mini Album"
    },
    {
        "rank": "24",
        "title": "REBEL HEART",
        "artist": "IVE (아이브)",
        "imageURL": "https://image.bugsm.co.kr/album/images/50/41130/4113098.jpg?version=20250213010511",
        "album": "IVE EMPATHY"
    },
    {
        "rank": "25",
        "title": "너에게 닿기를",
        "artist": "10CM",
        "imageURL": "https://image.bugsm.co.kr/album/images/50/41159/4115921.jpg?version=20250307105703",
        "album": "너에게 닿기를"
    },
    {
        "rank": "26",
        "title": "FAMOUS",
        "artist": "ALLDAY PROJECT",
        "imageURL": "https://image.bugsm.co.kr/album/images/50/41214/4121434.jpg?version=20251203014837",
        "album": "FAMOUS"
    },
    {
        "rank": "27",
        "title": "HAPPY",
        "artist": "DAY6 (데이식스)",
        "imageURL": "https://image.bugsm.co.kr/album/images/50/206298/20629850.jpg?version=20250104012829",
        "album": "Fourever"
    },
    {
        "rank": "28",
        "title": "Whiplash",
        "artist": "aespa",
        "imageURL": "https://image.bugsm.co.kr/album/images/50/41087/4108755.jpg?version=20241126004739",
        "album": "Whiplash - The 5th Mini Album"
    },
    {
        "rank": "29",
        "title": "모르시나요(PROD.로코베리)",
        "artist": "조째즈",
        "imageURL": "https://image.bugsm.co.kr/album/images/50/41125/4112579.jpg?version=20250108003805",
        "album": "모르시나요"
    },
    {
        "rank": "30",
        "title": "내게 사랑이 뭐냐고 물어본다면",
        "artist": "로이킴",
        "imageURL": "https://image.bugsm.co.kr/album/images/50/206771/20677117.jpg?version=20251125081353",
        "album": "내게 사랑이 뭐냐고 물어본다면"
    },
    {
        "rank": "31",
        "title": "XOXZ",
        "artist": "IVE (아이브)",
        "imageURL": "https://image.bugsm.co.kr/album/images/50/41260/4126044.jpg?version=20250828003754",
        "album": "IVE SECRET"
    },
    {
        "rank": "32",
        "title": "어떻게 이별까지 사랑하겠어, 널 사랑하는 거지",
        "artist": "AKMU(악뮤)",
        "imageURL": "https://image.bugsm.co.kr/album/images/50/202788/20278851.jpg?version=20210727012601",
        "album": "항해"
    },
    {
        "rank": "33",
        "title": "첫 만남은 계획대로 되지 않아",
        "artist": "TWS (투어스)",
        "imageURL": "https://image.bugsm.co.kr/album/images/50/40947/4094730.jpg?version=20250923013257",
        "album": "TWS 1st Mini Album ‘Sparkling Blue’"
    },
    {
        "rank": "34",
        "title": "모든 날, 모든 순간 (Every day, Every Moment)",
        "artist": "폴킴(Paul Kim)",
        "imageURL": "https://image.bugsm.co.kr/album/images/50/201547/20154722.jpg?version=20230601001519",
        "album": "'키스 먼저 할까요?' OST Part.3"
    },
    {
        "rank": "35",
        "title": "한 페이지가 될 수 있게",
        "artist": "DAY6 (데이식스)",
        "imageURL": "https://image.bugsm.co.kr/album/images/50/202657/20265759.jpg?version=20211119004415",
        "album": "The Book of Us : Gravity"
    },
    {
        "rank": "36",
        "title": "Love Me More",
        "artist": "Apink (에이핑크)",
        "imageURL": "https://image.bugsm.co.kr/album/images/50/41374/4137434.jpg?version=20260109013418",
        "album": "RE : LOVE"
    },
    {
        "rank": "37",
        "title": "Ditto",
        "artist": "NewJeans",
        "imageURL": "https://image.bugsm.co.kr/album/images/50/40824/4082425.jpg?version=20231215003716",
        "album": "NewJeans 'OMG'"
    },
    {
        "rank": "38",
        "title": "Die With A Smile",
        "artist": "Lady Gaga(레이디 가가)",
        "imageURL": "https://image.bugsm.co.kr/album/images/50/356136/35613643.jpg?version=20250701002559",
        "album": "Die With A Smile"
    },
    {
        "rank": "39",
        "title": "달리 표현할 수 없어요",
        "artist": "로이킴",
        "imageURL": "https://image.bugsm.co.kr/album/images/50/41316/4131664.jpg?version=20251029004137",
        "album": "달리 표현할 수 없어요"
    },
    {
        "rank": "40",
        "title": "나는 반딧불",
        "artist": "황가람",
        "imageURL": "https://image.bugsm.co.kr/album/images/50/41087/4108756.jpg?version=20241023010353",
        "album": "나는 반딧불"
    },
    {
        "rank": "41",
        "title": "오늘만 I LOVE YOU",
        "artist": "BOYNEXTDOOR",
        "imageURL": "https://image.bugsm.co.kr/album/images/50/41125/4112558.jpg?version=20250108011423",
        "album": "오늘만 I LOVE YOU"
    },
    {
        "rank": "42",
        "title": "HOME SWEET HOME (feat. 태양, 대성)",
        "artist": "G-DRAGON",
        "imageURL": "https://image.bugsm.co.kr/album/images/50/41106/4110623.jpg?version=20241128002601",
        "album": "HOME SWEET HOME (feat. 태양, 대성)"
    },
    {
        "rank": "43",
        "title": "청춘만화",
        "artist": "이무진",
        "imageURL": "https://image.bugsm.co.kr/album/images/50/41081/4108180.jpg?version=20250318024429",
        "album": "만화 (滿花)"
    },
    {
        "rank": "44",
        "title": "시작의 아이 ❍",
        "artist": "박다혜",
        "imageURL": "https://image.bugsm.co.kr/album/images/50/41248/4124853.jpg?version=20250812013338",
        "album": "시작의 아이 ❍ ハジマリのコ Starting With You : ♡"
    },
    {
        "rank": "45",
        "title": "number one girl",
        "artist": "로제(ROSÉ)",
        "imageURL": "https://image.bugsm.co.kr/album/images/50/41106/4110641.jpg?version=20241123003542",
        "album": "number one girl"
    },
    {
        "rank": "46",
        "title": "Soda Pop",
        "artist": "Saja Boys",
        "imageURL": "https://image.bugsm.co.kr/album/images/50/381763/38176338.jpg?version=20250927005933",
        "album": "KPop Demon Hunters (Soundtrack from the Netflix Film)"
    },
    {
        "rank": "47",
        "title": "APT.",
        "artist": "로제(ROSÉ)",
        "imageURL": "https://image.bugsm.co.kr/album/images/50/41086/4108664.jpg?version=20241206010201",
        "album": "APT."
    },
    {
        "rank": "48",
        "title": "I DO ME",
        "artist": "KiiiKiii (키키)",
        "imageURL": "https://image.bugsm.co.kr/album/images/50/41150/4115087.jpg?version=20250425011550",
        "album": "UNCUT GEM"
    },
    {
        "rank": "49",
        "title": "I AM",
        "artist": "IVE (아이브)",
        "imageURL": "https://image.bugsm.co.kr/album/images/50/40849/4084947.jpg?version=20240810012634",
        "album": "I've IVE"
    },
    {
        "rank": "50",
        "title": "주저하는 연인들을 위해",
        "artist": "잔나비",
        "imageURL": "https://image.bugsm.co.kr/album/images/50/202371/20237198.jpg?version=20210421045158",
        "album": "전설"
    },
    {
        "rank": "51",
        "title": "Love wins all",
        "artist": "아이유(IU)",
        "imageURL": "https://image.bugsm.co.kr/album/images/50/40955/4095501.jpg?version=20250326042636",
        "album": "The Winning"
    },
    {
        "rank": "52",
        "title": "천상연",
        "artist": "이창섭",
        "imageURL": "https://image.bugsm.co.kr/album/images/50/40963/4096392.jpg?version=20240222064728",
        "album": "천상연 (웹툰 '선녀외전' X 이창섭 (LEE CHANGSUB))"
    },
    {
        "rank": "53",
        "title": "DUET",
        "artist": "지코 (ZICO)",
        "imageURL": "https://image.bugsm.co.kr/album/images/50/41362/4136205.jpg?version=20251220020753",
        "album": "DUET"
    },
    {
        "rank": "54",
        "title": "Congratulations",
        "artist": "DAY6 (데이식스)",
        "imageURL": "https://image.bugsm.co.kr/album/images/50/5297/529710.jpg?version=20190719114948",
        "album": "The Day"
    },
    {
        "rank": "55",
        "title": "Zoo (From \"Zootopia 2\")",
        "artist": "Disney",
        "imageURL": "https://image.bugsm.co.kr/album/images/50/388975/38897538.jpg?version=20251220004005",
        "album": "Zoo (From \"Zootopia 2\")"
    },
    {
        "rank": "56",
        "title": "Dirty Work",
        "artist": "aespa",
        "imageURL": "https://image.bugsm.co.kr/album/images/50/41210/4121085.jpg?version=20250628011258",
        "album": "Dirty Work"
    },
    {
        "rank": "57",
        "title": "힙합보단 사랑, 사랑보단 돈 (Feat. 베이식)",
        "artist": "노아주다(noahjooda)",
        "imageURL": "https://image.bugsm.co.kr/album/images/50/40723/4072374.jpg?version=20240223043339",
        "album": "M O T N O A H"
    },
    {
        "rank": "58",
        "title": "Supernova",
        "artist": "aespa",
        "imageURL": "https://image.bugsm.co.kr/album/images/50/41011/4101141.jpg?version=20241102010939",
        "album": "Armageddon - The 1st Album"
    },
    {
        "rank": "59",
        "title": "Magnetic",
        "artist": "아일릿(ILLIT)",
        "imageURL": "https://image.bugsm.co.kr/album/images/50/206323/20632324.jpg?version=20251125080152",
        "album": "SUPER REAL ME"
    },
    {
        "rank": "60",
        "title": "Rich Man",
        "artist": "aespa",
        "imageURL": "https://image.bugsm.co.kr/album/images/50/41272/4127287.jpg?version=20251023002442",
        "album": "Rich Man - The 6th Mini Album"
    },
    {
        "rank": "61",
        "title": "ATTITUDE",
        "artist": "IVE (아이브)",
        "imageURL": "https://image.bugsm.co.kr/album/images/50/41130/4113098.jpg?version=20250213010511",
        "album": "IVE EMPATHY"
    },
    {
        "rank": "62",
        "title": "에피소드",
        "artist": "이무진",
        "imageURL": "https://image.bugsm.co.kr/album/images/50/40941/4094127.jpg?version=20250101001125",
        "album": "에피소드"
    },
    {
        "rank": "63",
        "title": "Love me or Leave me",
        "artist": "DAY6 (데이식스)",
        "imageURL": "https://image.bugsm.co.kr/album/images/50/203237/20323788.jpg?version=20241114011724",
        "album": "The Book of Us : The Demon"
    },
    {
        "rank": "64",
        "title": "고민중독",
        "artist": "QWER",
        "imageURL": "https://image.bugsm.co.kr/album/images/50/40996/4099653.jpg?version=20240402065258",
        "album": "1st Mini Album 'MANITO'"
    },
    {
        "rank": "65",
        "title": "사랑인가 봐",
        "artist": "멜로망스(MeloMance)",
        "imageURL": "https://image.bugsm.co.kr/album/images/50/40713/4071363.jpg?version=20220330120007",
        "album": "사랑인가 봐 (사내맞선 OST 스페셜 트랙)"
    },
    {
        "rank": "66",
        "title": "소나기",
        "artist": "이클립스 (ECLIPSE)",
        "imageURL": "https://image.bugsm.co.kr/album/images/50/206352/20635260.jpg?version=20251125080244",
        "album": "선재 업고 튀어 OST Part 1"
    },
    {
        "rank": "67",
        "title": "body",
        "artist": "다영 (DAYOUNG)",
        "imageURL": "https://image.bugsm.co.kr/album/images/50/41275/4127586.jpg?version=20250923011626",
        "album": "gonna love me, right?"
    },
    {
        "rank": "68",
        "title": "빌려온 고양이 (Do the Dance)",
        "artist": "아일릿(ILLIT)",
        "imageURL": "https://image.bugsm.co.kr/album/images/50/41210/4121023.jpg?version=20251125051317",
        "album": "bomb"
    },
    {
        "rank": "69",
        "title": "Pookie",
        "artist": "FIFTY FIFTY",
        "imageURL": "https://image.bugsm.co.kr/album/images/50/377971/37797179.jpg?version=20250924011146",
        "album": "Day & Night"
    },
    {
        "rank": "70",
        "title": "Welcome to the Show",
        "artist": "DAY6 (데이식스)",
        "imageURL": "https://image.bugsm.co.kr/album/images/50/206298/20629850.jpg?version=20250104012829",
        "album": "Fourever"
    },
    {
        "rank": "71",
        "title": "예뻤어",
        "artist": "DAY6 (데이식스)",
        "imageURL": "https://image.bugsm.co.kr/album/images/50/200804/20080494.jpg?version=20240805121438",
        "album": "Every DAY6 February"
    },
    {
        "rank": "72",
        "title": "그대만 있다면 (여름날 우리 X 너드커넥션 (Nerd Connection))",
        "artist": "너드커넥션(Nerd Connection)",
        "imageURL": "https://image.bugsm.co.kr/album/images/50/40901/4090168.jpg?version=20240209005514",
        "album": "그대만 있다면 (여름날 우리 X 너드커넥션 (Nerd Connection))"
    },
    {
        "rank": "73",
        "title": "LOOK AT ME",
        "artist": "ALLDAY PROJECT",
        "imageURL": "https://image.bugsm.co.kr/album/images/50/41335/4133502.jpg?version=20251209003718",
        "album": "ALLDAY PROJECT"
    },
    {
        "rank": "74",
        "title": "STYLE",
        "artist": "Hearts2Hearts (하츠투하츠)",
        "imageURL": "https://image.bugsm.co.kr/album/images/50/41214/4121497.jpg?version=20250619013108",
        "album": "STYLE"
    },
    {
        "rank": "75",
        "title": "Mantra",
        "artist": "제니 (JENNIE)",
        "imageURL": "https://image.bugsm.co.kr/album/images/50/41083/4108354.jpg?version=20241017004618",
        "album": "Mantra"
    },
    {
        "rank": "76",
        "title": "Maybe Tomorrow",
        "artist": "DAY6 (데이식스)",
        "imageURL": "https://image.bugsm.co.kr/album/images/50/207241/20724195.jpg?version=20250508024718",
        "album": "Maybe Tomorrow"
    },
    {
        "rank": "77",
        "title": "Popcorn",
        "artist": "도경수(D.O.)",
        "imageURL": "https://image.bugsm.co.kr/album/images/50/206405/20640582.jpg?version=20251115002408",
        "album": "성장 - THE 3RD MINI ALBUM"
    },
    {
        "rank": "78",
        "title": "INSIDE OUT",
        "artist": "DAY6 (데이식스)",
        "imageURL": "https://image.bugsm.co.kr/album/images/50/207535/20753540.jpg?version=20250916011214",
        "album": "The DECADE"
    },
    {
        "rank": "79",
        "title": "눈물참기",
        "artist": "QWER",
        "imageURL": "https://image.bugsm.co.kr/album/images/50/41210/4121045.jpg?version=20250611010118",
        "album": "3rd Mini Album '난 네 편이야, 온 세상이 불협일지라도'"
    },
    {
        "rank": "80",
        "title": "내 이름 맑음",
        "artist": "QWER",
        "imageURL": "https://image.bugsm.co.kr/album/images/50/41065/4106548.jpg?version=20250107004107",
        "album": "2nd Mini Album 'Algorithm's Blossom'"
    },
    {
        "rank": "81",
        "title": "HOT",
        "artist": "LE SSERAFIM (르세라핌)",
        "imageURL": "https://image.bugsm.co.kr/album/images/50/41162/4116299.jpg?version=20251111013901",
        "album": "HOT"
    },
    {
        "rank": "82",
        "title": "나는 아픈 건 딱 질색이니까",
        "artist": "i-dle (아이들)",
        "imageURL": "https://image.bugsm.co.kr/album/images/50/40953/4095394.jpg?version=20250503021216",
        "album": "2"
    },
    {
        "rank": "83",
        "title": "Hype Boy",
        "artist": "NewJeans",
        "imageURL": "https://image.bugsm.co.kr/album/images/50/40780/4078016.jpg?version=20221014011218",
        "album": "NewJeans 1st EP 'New Jeans'"
    },
    {
        "rank": "84",
        "title": "HANDS UP",
        "artist": "MEOVV (미야오)",
        "imageURL": "https://image.bugsm.co.kr/album/images/50/41184/4118481.jpg?version=20250514021619",
        "album": "MY EYES OPEN VVIDE"
    },
    {
        "rank": "85",
        "title": "시작의 아이",
        "artist": "마크툽(MAKTUB)",
        "imageURL": "https://image.bugsm.co.kr/album/images/50/41124/4112411.jpg?version=20250618004611",
        "album": "시작의 아이 ハジマリのコ (Starting With You)"
    },
    {
        "rank": "86",
        "title": "Hollywood Action",
        "artist": "BOYNEXTDOOR",
        "imageURL": "https://image.bugsm.co.kr/album/images/50/41310/4131052.jpg?version=20251024004042",
        "album": "The Action"
    },
    {
        "rank": "87",
        "title": "Never Ending Story",
        "artist": "아이유(IU)",
        "imageURL": "https://image.bugsm.co.kr/album/images/50/41204/4120415.jpg?version=20250529011654",
        "album": "꽃갈피 셋"
    },
    {
        "rank": "88",
        "title": "Your Idol",
        "artist": "Saja Boys",
        "imageURL": "https://image.bugsm.co.kr/album/images/50/381763/38176338.jpg?version=20250927005933",
        "album": "KPop Demon Hunters (Soundtrack from the Netflix Film)"
    },
    {
        "rank": "89",
        "title": "365일",
        "artist": "이창섭",
        "imageURL": "https://image.bugsm.co.kr/album/images/50/41356/4135615.jpg?version=20251211180000",
        "album": "365일 (오늘 밤, 세계에서 이 사랑이 사라진다 해도 X 이창섭)"
    },
    {
        "rank": "90",
        "title": "TOO BAD (feat. Anderson .Paak)",
        "artist": "G-DRAGON",
        "imageURL": "https://image.bugsm.co.kr/album/images/50/41156/4115621.jpg?version=20250910003408",
        "album": "Übermensch"
    },
    {
        "rank": "91",
        "title": "첫 눈",
        "artist": "EXO",
        "imageURL": "https://image.bugsm.co.kr/album/images/50/4005/400586.jpg?version=20250107030153",
        "album": "겨울 스페셜 앨범 '12월의 기적 (Miracles in December)’"
    },
    {
        "rank": "92",
        "title": "WICKED",
        "artist": "ALLDAY PROJECT",
        "imageURL": "https://image.bugsm.co.kr/album/images/50/41214/4121434.jpg?version=20251203014837",
        "album": "FAMOUS"
    },
    {
        "rank": "93",
        "title": "사랑의 언어 (Love Language)",
        "artist": "김민석 (멜로망스)",
        "imageURL": "https://image.bugsm.co.kr/album/images/50/41383/4138305.jpg?version=20260123002424",
        "album": "이 사랑 통역 되나요? (Soundtrack from the Netflix Series)"
    },
    {
        "rank": "94",
        "title": "Flower",
        "artist": "오반(OVAN)",
        "imageURL": "https://image.bugsm.co.kr/album/images/50/41160/4116029.jpg?version=20250315024908",
        "album": "교회오빠"
    },
    {
        "rank": "95",
        "title": "꿈의 버스",
        "artist": "DAY6 (데이식스)",
        "imageURL": "https://image.bugsm.co.kr/album/images/50/207535/20753540.jpg?version=20250916011214",
        "album": "The DECADE"
    },
    {
        "rank": "96",
        "title": "You're Shining Star",
        "artist": "CUZCO",
        "imageURL": "https://image.bugsm.co.kr/album/images/50/207005/20700510.jpg?version=20250730024156",
        "album": "You're Shining Star"
    },
    {
        "rank": "97",
        "title": "한번 더 이별",
        "artist": "이창섭",
        "imageURL": "https://image.bugsm.co.kr/album/images/50/41262/4126265.jpg?version=20250828022008",
        "album": "한번 더 이별 (첫사랑 엔딩 X 이창섭)"
    },
    {
        "rank": "98",
        "title": "바이, 썸머",
        "artist": "아이유(IU)",
        "imageURL": "https://image.bugsm.co.kr/album/images/50/41276/4127630.jpg?version=20250911013055",
        "album": "바이, 썸머"
    },
    {
        "rank": "99",
        "title": "돌아오는 길 (feat. CUZCO)",
        "artist": "성연(SUNGYEON)",
        "imageURL": "https://image.bugsm.co.kr/album/images/50/206730/20673041.jpg?version=20241002120043",
        "album": "돌아오는 길 (feat. CUZCO)"
    },
    {
        "rank": "100",
        "title": "Drive Life",
        "artist": "CUZCO",
        "imageURL": "https://image.bugsm.co.kr/album/images/50/206533/20653359.jpg?version=20250107002926",
        "album": "Drive Life"
    }
]